Workbook

Sheet Read me
A1: Frisbii MCP Skills Pack and "Skill of the Week" launch plan
A3: Purpose | B3: Defines the installable skills pack for the Frisbii MCP server, flags overlap with the Kvitora collections agent, and lays out a 13-week marketing series to drive adoption (26 Oct 2026 to 18 Jan 2027).
A4: Tabs | B4: Skills: the full skill list with product fit, Kvitora risk and release timing. Kvitora clashes: skills that could substitute for the collections agent, and how each hands off to it. 13-week plan: weekly episodes by audience, with channels, Kvitora tie-ins and KPIs. Summary: live counts that update as you edit the other tabs.
A5: Cells to edit | B5: Yellow cells are for your team to fill in: owners, status, MCP validation results and KPI targets. Status and validation columns have drop-down lists. Everything else is a working draft and can be changed freely.
A6: Example entry | B6: Owner: "Product marketing". Status: "In progress". MCP validation: "Works on both". Target installs: 50.
A7: Product labels | B7: Pay = Frisbii Pay. Billing = Frisbii Billing. Both = works on either. Skills labelled Billing may also work for Pay merchants who run subscriptions on Pay; the "Test on Pay?" column flags these for validation.
A8: Key dates | B8: Black Friday 27 Nov 2026. Cyber Monday 30 Nov 2026. Month ends 30 Oct, 30 Nov, 31 Dec. Q4 / year end 31 Dec.
A9: Assumptions | B9: Skill-to-MCP-tool mapping is not yet validated. Proposed Pay skills (payout reconciliation, dispute monitor, payment-method mix) depend on the MCP exposing payout, dispute and method-level data. plan-performance waits on the list_plans fix. All first-quarter skills are read-only.
A10: Ground rules | B10: No skill drafts or sends customer outreach about unpaid invoices; that is Kvitora's job. Every payment-failure skill ends with a Kvitora handoff. Each skill is released a few days before its episode.
A11: Update 20 Oct 2026 | B11: Skills tab: added MCP feasibility, feasibility notes and main MCP tools (columns M–O), mapped from the live Frisbii Billing & Pay MCP tool list (source: docs/mcp-tool-map.md in frisbii-com/frisbii-mcp-skills). Added repo status and a link to each skill's Confluence page (columns P–Q, space SKILL). Owner set to Martyn Arbon. 'MCP validation' stays 'Not validated': the MCP entitlement is not yet enabled on the test accounts, so no skill has run on live data.
A12: Kvitora decision (19 Oct 2026) | B12: For the skills, Kvitora is treated as out of scope: skills end with neutral recovery next steps instead of a Kvitora handoff, and may draft customer messages for the merchant to send (still read-only). The Kvitora risk column and Kvitora clashes tab are kept for reference only.

Sheet Skills
A1: # | B1: Skill | C1: Category | D1: What it does for the merchant | E1: Product | F1: Test on Pay? | G1: Kvitora risk | H1: Featured week | I1: Release status | J1: Dependencies / notes | K1: MCP validation | L1: Owner | M1: MCP feasibility (20 Oct 2026) | N1: Feasibility notes (live MCP tools) | O1: Main MCP tools | P1: Repo status | Q1: Confluence page
A2: 1 | B2: frisbii-core | C2: Foundation | D2: Checks the connection, detects Pay vs Billing, paces calls for the rate limit, enforces read-only defaults and consistent currency/date formatting. Every other skill relies on it. | E2: Both | F2: n/a | G2: None | H2: 1 | I2: Core | J2: Rate limit ~3 calls/min must be handled here. | K2: Not validated | L2: Martyn Arbon | M2: Feasible | N2: Pay/Billing detection is a heuristic (live subscriptions vs settled transactions) | O2: get_account, get_token_allowance, count_subscriptions, count_transactions | P2: Drafted, not validated | Q2: https://billwerk.atlassian.net/wiki/spaces/SKILL/pages/11604164621
A3: 2 | B3: month-end-close | C3: Revenue & reporting | D3: MRR snapshot, new vs churned subscriptions, open vs paid invoices for the month. | E3: Billing | F3: Yes | G3: None | H3: 1 | I3: Series | J3: Launch episode. Refresher in week 6 for November close. | K3: Not validated | L3: Martyn Arbon | M3: Feasible | N3: MRR is "as of snapshot", not "at month end". Opening MRR not derivable | O3: get_subscription_revenue, get_committed_recurring_revenue, count_subscriptions, count_invoices, get_refunds | P3: Drafted, not validated | Q3: https://billwerk.atlassian.net/wiki/spaces/SKILL/pages/11603771396
A4: 3 | B4: customer-360 | C4: Customer | D4: Everything about one customer before a call: plan, payment history, failures, invoices. | E4: Both | F4: n/a | G4: Low | H4: 2 | I4: Series | J4: Show overdue status only; never suggest outreach. | K4: Not validated | L4: Martyn Arbon | M4: Feasible | N4: No known gaps | O4: get_customer_billing_overview, list_customers, resolve_handle, get_customer_balance, get_subscription_revenue, get_dunning_status | P4: Drafted, not validated | Q4: https://billwerk.atlassian.net/wiki/spaces/SKILL/pages/11603902520
A5: 4 | B5: card-expiry-sweep | C5: Payments & recovery | D5: Customers whose card expires before their next renewal. | E5: Pay | F5: n/a | G5: Low | H5: 3 | I5: Series | J5: Preventive, so it complements Kvitora. Must not draft customer emails. | K5: Not validated | L5: Martyn Arbon | M5: Partly feasible | N5: No expiry filter or count tool, so it means paging every payment method at 3 calls/min. Check whether create_report_export offers a payment-method report; otherwise limit to the top N customers by revenue | O5: list_payment_methods (has exp_date), list_subscriptions | P5: Drafted, not validated | Q5: https://billwerk.atlassian.net/wiki/spaces/SKILL/pages/11603869698
A6: 5 | B6: account-hygiene | C6: Operations | D6: Stale trials, subscriptions with no payment method, leftover test data. | E6: Both | F6: n/a | G6: None | H6: 3 | I6: Series (Billing alt.) | J6: Billing audience alternative in week 3. | K6: Not validated | L6: Martyn Arbon | M6: Partly feasible | N6: "Subscription with no payment method" isn't filterable | O6: count_subscriptions (state=pending,on_hold), list_customers (test flag), count_customers | P6: Drafted, not validated | Q6: https://billwerk.atlassian.net/wiki/spaces/SKILL/pages/11604590625
A7: 6 | B7: promo-readiness | C7: Pricing & promotions | D7: Pre-campaign check of coupons, discounts and plan setup. | E7: Billing | F7: Yes | G7: None | H7: 4 | I7: Series | J7: Partly depends on plan data; check list_plans fix status. | K7: Not validated | L7: Martyn Arbon | M7: Feasible | N7: Plan names need list_plans (bug status untested) | O7: list_coupons state=active, list_discounts, get_plan, list_plans | P7: Drafted, not validated | Q7: https://billwerk.atlassian.net/wiki/spaces/SKILL/pages/11603705881
A8: 7 | B8: payment-method-mix | C8: Payments & recovery | D8: Payment-method mix and success rates by market (e.g. card vs MobilePay). | E8: Pay | F8: n/a | G8: None | H8: 4 | I8: Proposed | J8: Needs method-level data from the MCP. Pay alternative in week 4. | K8: Not validated | L8: Martyn Arbon | M8: Partly feasible | N8: Settled-date filters exclude failures, so success rates are all-time while the period mix is settled-only. No per-country method cross-tab | O8: count_transactions (settled window, group_by=payment_type; all-time group_by=payment_type,state), count_open_transactions per method, count_customers group_by=country | P8: Drafted, not validated | Q8: https://billwerk.atlassian.net/wiki/spaces/SKILL/pages/11604295692
A9: 8 | B9: peak-pulse | C9: Payments & recovery | D9: Live view of sign-ups and payment success by method during a peak, paced for rate limits. | E9: Pay | F9: n/a | G9: None | H9: 5 | I9: Series | J9: Highest rate-limit risk. Batch calls; consider a temporary limit increase for BFCM week. | K9: Not validated | L9: Martyn Arbon | M9: Feasible | N9: Settled-window transactions exclude failures, so the success rate comes from invoice states. Snapshot lag is "typically minutes", so it isn't truly live. Say so in the episode. 3 calls per refresh | O9: count_transactions (settled window, group_by=payment_type), count_invoices (created window, group_by=state) for the success rate, count_subscriptions (created window) | P9: Drafted, not validated | Q9: https://billwerk.atlassian.net/wiki/spaces/SKILL/pages/11604230686
A10: 9 | B10: failed-payment-triage | C10: Payments & recovery | D10: Failed payments grouped by reason, recoverable vs not, top accounts at risk. | E10: Pay | F10: n/a | G10: High | H10: 6 | I10: Series | J10: Ship only with Kvitora handoff. If Kvitora isn't live by late Nov, move this episode later. | K10: Not validated | L10: Martyn Arbon | M10: Feasible | N10: Grouping failures by reason means the export (acquirer codes) or paging list_failed_payments (one-month default) | O10: count_invoices state=failed/dunning, count_open_transactions, investigate_failed_or_overdue_billing, list_failed_payments, create_report_export report=open_transactions | P10: Drafted, not validated | Q10: https://billwerk.atlassian.net/wiki/spaces/SKILL/pages/11603902545
A11: 10 | B11: promo-cohort-quality | C11: Pricing & promotions | D11: How discount-acquired subscribers behave compared with full-price ones. | E11: Billing | F11: Yes | G11: None | H11: 7 | I11: Series | J11: Early read in Dec; repeat in Feb for a fuller picture. | K11: Not validated | L11: Martyn Arbon | M11: Partly feasible | N11: No direct discounted vs full-price filter on count_subscriptions. Needs the export joined to subscription state | O11: count_subscription_discounts, create_report_export report=subscription_discounts, count_subscriptions | P11: Drafted, not validated | Q11: https://billwerk.atlassian.net/wiki/spaces/SKILL/pages/11603705904
A12: 11 | B12: dispute-monitor | C12: Payments & recovery | D12: Chargebacks and disputes after a peak period, by reason and amount. | E12: Pay | F12: n/a | G12: None | H12: 7 | I12: Proposed | J12: Needs dispute data from the MCP. Pay alternative in week 7. | K12: Not validated | L12: Martyn Arbon | M12: Feasible | N12: Aggregates only, no per-dispute rows | O12: count_disputes group_by=reason,outcome,state | P12: Drafted, not validated | Q12: https://billwerk.atlassian.net/wiki/spaces/SKILL/pages/11603902568
A13: 12 | B13: renewal-radar | C13: Customer | D13: Annual and high-value renewals coming up in the next 30-60 days. | E13: Billing | F13: Yes | G13: None | H13: 8 | I13: Series | K13: Not validated | L13: Martyn Arbon | M13: Partly feasible | N13: No renewal-date filter, so it pages subscriptions per annual plan | O13: list_subscriptions (next renewal), get_plan (interval), get_committed_recurring_revenue | P13: Drafted, not validated | Q13: https://billwerk.atlassian.net/wiki/spaces/SKILL/pages/11604557894
A14: 13 | B14: year-in-review | C14: Revenue & reporting | D14: Shareable annual recap: payment volume (Pay) or recurring revenue growth (Billing), top plans, milestones. | E14: Both | F14: n/a | G14: None | H14: 9 | I14: Series | J14: Light holiday-week episode; designed to be shared on LinkedIn. | K14: Not validated | L14: Martyn Arbon | M14: Feasible | N14: No known gaps | O14: count_transactions (year, group_by=payment_type), get_subscription_revenue, count_subscriptions, count_customers | P14: Drafted, not validated | Q14: https://billwerk.atlassian.net/wiki/spaces/SKILL/pages/11603935243
A15: 14 | B15: board-pack | C15: Revenue & reporting | D15: Quarter- or year-end summary: MRR movement, retention, cohorts, plan mix. | E15: Billing | F15: Yes | G15: None | H15: 11 | I15: Series | J15: Showcase for branded deck output. | K15: Not validated | L15: Martyn Arbon | M15: Feasible | N15: No known gaps | O15: as month-end-close over a quarter, plus count_customers, get_add_on_revenue | P15: Drafted, not validated | Q15: https://billwerk.atlassian.net/wiki/spaces/SKILL/pages/11604328484
A16: 15 | B16: payout-reconciliation | C16: Revenue & reporting | D16: Reconciles payouts and settlements against transactions for the period. The Pay equivalent of month-end close. | E16: Pay | F16: n/a | G16: None | H16: 1 | I16: Proposed | J16: Needs payout/settlement data from the MCP. Pay alternative in weeks 1 and 11. | K16: Not validated | L16: Martyn Arbon | M16: Feasible | N16: Keep major- and minor-unit sources apart | O16: reconcile_payout_window (pass currency), list_payouts, list_settlements (major units), get_settlement_report | P16: Drafted, not validated | Q16: https://billwerk.atlassian.net/wiki/spaces/SKILL/pages/11604131862
A17: 16 | B17: churn-and-retention | C17: Revenue & reporting | D17: Voluntary vs involuntary churn, trends, at-risk segments. | E17: Billing | F17: Yes | G17: Medium | H17: 12 | I17: Series | J17: Involuntary-churn section must hand off to Kvitora. | K17: Not validated | L17: Martyn Arbon | M17: Partly feasible | N17: The voluntary vs involuntary split (expire_reason=dunning) isn't a count filter. Check group_by options or the export. Uses the recovery next steps | O17: count_subscriptions ended_*, get_subscription_revenue ended_*, get_committed_recurring_revenue | P17: Drafted, not validated | Q17: https://billwerk.atlassian.net/wiki/spaces/SKILL/pages/11604066330
A18: 17 | B18: dunning-review | C18: Payments & recovery | D18: Reframed as a Kvitora performance report: recovery rate, money recovered, time to payment. Shows the opportunity for merchants not yet using Kvitora. | E18: Pay | F18: n/a | G18: High | H18: 13 | I18: Series (Pay alt.) | J18: Only ship in the Kvitora-report framing. Could become Both if Billing dunning data is exposed. | K18: Not validated | L18: Martyn Arbon | M18: Partly feasible | N18: Recovery rate comes from settled invoices that carry a dunning timestamp, via paged list_invoices, so it's sample-based on large accounts. Confirm the timestamp field exists | O18: list_dunning_plans, count_invoices dunning_invoices=true, investigate_dunning_invoices, list_invoices state=settled/failed | P18: Drafted, not validated | Q18: https://billwerk.atlassian.net/wiki/spaces/SKILL/pages/11604393997
A19: 18 | B19: migration-from-transform | C19: Migration | D19: Guides Frisbii Transform customers through moving to Frisbii Billing. | E19: Billing | F19: n/a | G19: None | H19: 13 | I19: Series | J19: Kicks off a Q1 migration mini-series aimed at Transform customers. | K19: Not validated | L19: Martyn Arbon | M19: Partly feasible | N19: Mostly guidance content. The MCP has no Transform-side data | O19: get_account, count_* for a post-migration check | P19: Drafted, not validated | Q19: https://billwerk.atlassian.net/wiki/spaces/SKILL/pages/11604492293
A20: 19 | B20: plan-performance | C20: Pricing & promotions | D20: Which plans grow, churn and get discounted. | E20: Billing | F20: Yes | G20: None | I20: Later | J20: Blocked on the list_plans parsing bug. | K20: Not validated | L20: Martyn Arbon | M20: Feasible (likely) | N20: No longer blocked by list_plans except for display names. Discounts per plan only via coupon eligibility or the subscription_discounts export | O20: get_subscription_revenue group_by=plan, count_subscriptions group_by=plan (live, created, ended), get_committed_recurring_revenue group_by=plan, list_plans (names), list_coupons | P20: Drafted, not validated | Q20: https://billwerk.atlassian.net/wiki/spaces/SKILL/pages/11604000773

Sheet Kvitora clashes
A1: Skill | B1: Kvitora risk | C1: Featured week | D1: Why it could clash | E1: Mitigation | F1: Suggested handoff line in the skill output | G1: Must never do
A2: failed-payment-triage | B2: High | C2: =IFERROR(INDEX(Skills!$H$2:$H$20,MATCH(A2,Skills!$B$2:$B$20,0)),"-") -> 6 | D2: Lists who hasn't paid and which payments are recoverable, which is the starting point for chasing them by hand. | E2: End with a recoverable-amount summary and a Kvitora handoff. If Kvitora is active, show what it is already working on. | F2: "EUR X across Y customers is recoverable. Kvitora can work these automatically: [set up / view progress]." | G2: Produce a chase list formatted for sending, or draft reminder emails.
A3: dunning-review | B3: High | C3: =IFERROR(INDEX(Skills!$H$2:$H$20,MATCH(A3,Skills!$B$2:$B$20,0)),"-") -> 13 | D3: As a retry-outcome review it sits squarely in the collections agent's space. | E3: Reframe as a Kvitora performance report for agent users, and a "what you're leaving on the table" view for non-users. | F3: "Kvitora recovered EUR X this month (Y% recovery rate)." / "An estimated EUR X went unrecovered. See how Kvitora would handle it." | G3: Recommend manual dunning sequences or retry schedules.
A4: churn-and-retention | B4: Medium | C4: =IFERROR(INDEX(Skills!$H$2:$H$20,MATCH(A4,Skills!$B$2:$B$20,0)),"-") -> 12 | D4: The involuntary-churn section surfaces the same customers Kvitora targets. | E4: Keep the involuntary-churn section diagnostic and route it to Kvitora. | F4: "Z% of churn this quarter was involuntary. Kvitora is designed to recover these customers." | G4: Suggest contacting churned or overdue customers directly.
A5: card-expiry-sweep | B5: Low | C5: =IFERROR(INDEX(Skills!$H$2:$H$20,MATCH(A5,Skills!$B$2:$B$20,0)),"-") -> 3 | D5: Mostly preventive, but would overlap if it started generating customer outreach. | E5: Keep it as an internal list for the merchant's team. Position as complementary to Kvitora. | F5: "Expiring cards are the most common cause of future failed payments. Kvitora picks up any that slip through." | G5: Draft emails asking customers to update their card.
A6: customer-360 | B6: Low | C6: =IFERROR(INDEX(Skills!$H$2:$H$20,MATCH(A6,Skills!$B$2:$B$20,0)),"-") -> 2 | D6: Shows overdue status for a single customer. | E6: Show status only, with a note when Kvitora is already handling the account. | F6: "This account has an overdue invoice, currently being handled by Kvitora." | G6: Suggest how to chase the customer.
A8: Ground rules for every skill in the pack
A9: 1. Skills diagnose; Kvitora acts. No skill drafts, schedules or sends customer outreach about unpaid invoices.
A10: 2. Any skill that surfaces failed or overdue payments ends with a Kvitora handoff, agent-aware (shows Kvitora progress if active, the opportunity if not).
A11: 3. No write actions that contact customers, now or in later versions of the pack.
A12: 4. If Kvitora is not generally available by late November, move failed-payment-triage later rather than ship it without the handoff.

Sheet 13-week plan
A1: Week | B1: Week of | C1: Calendar moment | D1: Theme | E1: Primary skill | F1: Primary audience | G1: Alternate for other audience | H1: Episode hook | I1: Kvitora tie-in | J1: Channels | K1: Skill ready by | L1: Primary KPI | M1: Target installs | N1: Owner | O1: Status
A2: 1 | B2: 46321 | C2: October month end (30 Oct) | D2: Launch: close October in minutes | E2: month-end-close | F2: Billing | G2: payout-reconciliation (Pay, proposed) | H2: Your month-end close, done by an assistant before your coffee cools. | I2: - | J2: Email (segmented by product), in-app/dashboard banner, LinkedIn clip, skills library page; launch announcement + CSM outreach | K2: 46317 | L2: Pack installs; MCP connections | O2: Not started
A3: 2 | B3: 46328 | C3: - | D3: Know your customer | E3: customer-360 | F3: Both | G3: - | H3: Walk into every call knowing everything. | I3: Shows when Kvitora is handling an overdue account. | J3: Email (segmented by product), in-app/dashboard banner, LinkedIn clip, skills library page; CS and sales enablement | K3: 46324 | L3: Installs; tool calls in 7 days | O3: Not started
A4: 3 | B4: 46335 | C4: Black Friday prep #1 | D4: Fix expiring cards before the peak | E4: card-expiry-sweep | F4: Pay | G4: account-hygiene (Billing) | H4: Fix expiring cards before your biggest weekend, not after. | I4: Kvitora catches whatever slips through. | J4: Email (segmented by product), in-app/dashboard banner, LinkedIn clip, skills library page | K4: 46331 | L4: Installs; tool calls in 7 days | O4: Not started
A5: 4 | B5: 46342 | C5: Black Friday prep #2 | D5: Campaign readiness check | E5: promo-readiness | F5: Billing | G5: payment-method-mix (Pay, proposed) | H5: Check your campaign setup before customers find the mistakes. | I5: - | J5: Email (segmented by product), in-app/dashboard banner, LinkedIn clip, skills library page; BFCM readiness webinar (optional) | K5: 46338 | L5: Installs; tool calls in 7 days | O5: Not started
A6: 5 | B6: 46349 | C6: Black Friday 27 Nov | D6: Watch your peak live | E6: peak-pulse | F6: Pay | G6: peak-pulse sign-up view (Billing, if supported) | H6: Watch your peak as it happens. | I6: - | J6: Email (segmented by product), in-app/dashboard banner, LinkedIn clip, skills library page; send Mon 23 Nov, reminder Fri 27 Nov | K6: 46345 | L6: Tool calls during BFCM weekend; error/rate-limit rate | O6: Not started
A7: 6 | B7: 46356 | C7: Cyber Monday 30 Nov; November month end | D7: Recover what the rush left behind | E7: failed-payment-triage | F7: Pay | G7: month-end-close refresher (Billing) | H7: Recover what the rush left behind. | I7: Main Kvitora feature: size of the recoverable amount, Kvitora as the fix. | J7: Email (segmented by product), in-app/dashboard banner, LinkedIn clip, skills library page; Kvitora co-marketing | K7: 46352 | L7: Kvitora sign-ups from handoff; installs | O7: Not started
A8: 7 | B8: 46363 | C8: Post-BFCM | D8: Did they stick? | E8: promo-cohort-quality | F8: Billing | G8: dispute-monitor (Pay, proposed) | H8: Were your Black Friday customers worth the discount? | I8: - | J8: Email (segmented by product), in-app/dashboard banner, LinkedIn clip, skills library page | K8: 46359 | L8: Installs; tool calls in 7 days | O8: Not started
A9: 8 | B9: 46370 | C9: Pre-January renewals | D9: Get ahead of January | E9: renewal-radar | F9: Billing | G9: card-expiry-sweep refresher (Pay) | H9: Know which renewals matter before the new year. | I9: - | J9: Email (segmented by product), in-app/dashboard banner, LinkedIn clip, skills library page; CSM nudge for annual-contract merchants | K9: 46366 | L9: Installs; tool calls in 7 days | O9: Not started
A10: 9 | B10: 46377 | C10: Holiday week | D10: Your year in billing | E10: year-in-review | F10: Both | G10: - | H10: Your year in billing, in one prompt. | I10: - | J10: Email (segmented by product), in-app/dashboard banner, LinkedIn clip, skills library page; encourage merchants to share on LinkedIn | K10: 46373 | L10: Installs; social shares | O10: Not started
A11: 10 | B11: 46384 | C11: Holiday break | D11: Library roundup (no new skill) | E11: - | F11: Both | G11: - | H11: The skills pack so far, and the best uses we've seen. | I11: Recap Kvitora results from week 6. | J11: Email + skills library page only | L11: Library page visits; catch-up installs | O11: Not started
A12: 11 | B12: 46391 | C12: Q4 / year-end close | D12: The board slide you don't have to build | E12: board-pack | F12: Billing | G12: payout-reconciliation (Pay, proposed) | H12: The board slide you don't have to build. | I12: - | J12: Email (segmented by product), in-app/dashboard banner, LinkedIn clip, skills library page; CSM use in Q1 QBRs | K12: 46387 | L12: Installs; tool calls in 7 days | O12: Not started
A13: 12 | B13: 46398 | C13: January churn season | D13: Spot cancellations before they happen | E13: churn-and-retention | F13: Billing | G13: failed-payment-triage refresher (Pay) | H13: Spot the cancellations before they happen. | I13: Involuntary churn routed to Kvitora. | J13: Email (segmented by product), in-app/dashboard banner, LinkedIn clip, skills library page | K13: 46394 | L13: Installs; Kvitora sign-ups from handoff | O13: Not started
A14: 13 | B14: 46405 | C14: Start of Q1 migration push | D14: Moving to Frisbii Billing | E14: migration-from-transform | F14: Transform customers | G14: dunning-review / Kvitora report (Pay) | H14: Moving to Frisbii Billing, step by step. | I14: Pay alternative is the Kvitora performance report. | J14: Targeted email to Transform customers, CSM outreach, webinar | K14: 46401 | L14: Migration skill installs; migration starts | O14: Not started
L15: Total target installs | M15: =SUM(M2:M14) -> 0
A17: Skill ready by = release date, a few days before the episode, so early adopters can test it. Proposed Pay skills depend on MCP data availability; if unavailable, Pay merchants skip that week.

Sheet Summary
A1: Summary (updates automatically)
A3: Skills by product
A4: Product | B4: Count
A5: Pay | B5: =COUNTIF(Skills!$E$2:$E$20,A5) -> 7
A6: Billing | B6: =COUNTIF(Skills!$E$2:$E$20,A6) -> 8
A7: Both | B7: =COUNTIF(Skills!$E$2:$E$20,A7) -> 4
A8: Total | B8: =SUM(B5:B7) -> 19
A10: Skills by Kvitora risk
A11: Kvitora risk | B11: Count
A12: High | B12: =COUNTIF(Skills!$G$2:$G$20,A12) -> 2
A13: Medium | B13: =COUNTIF(Skills!$G$2:$G$20,A13) -> 1
A14: Low | B14: =COUNTIF(Skills!$G$2:$G$20,A14) -> 2
A15: None | B15: =COUNTIF(Skills!$G$2:$G$20,A15) -> 14
A16: Total | B16: =SUM(B12:B15) -> 19
A18: Skills by release status
A19: Release status | B19: Count
A20: Core | B20: =COUNTIF(Skills!$I$2:$I$20,A20) -> 1
A21: Series | B21: =COUNTIF(Skills!$I$2:$I$20,A21) -> 12
A22: Series (Billing alt.) | B22: =COUNTIF(Skills!$I$2:$I$20,A22) -> 1
A23: Series (Pay alt.) | B23: =COUNTIF(Skills!$I$2:$I$20,A23) -> 1
A24: Proposed | B24: =COUNTIF(Skills!$I$2:$I$20,A24) -> 3
A25: Later | B25: =COUNTIF(Skills!$I$2:$I$20,A25) -> 1
A26: Total | B26: =SUM(B20:B25) -> 19
A28: Episodes by primary audience
A29: Audience | B29: Count
A30: Pay | B30: =COUNTIF('13-week plan'!$F$2:$F$14,A30) -> 3
A31: Billing | B31: =COUNTIF('13-week plan'!$F$2:$F$14,A31) -> 6
A32: Both | B32: =COUNTIF('13-week plan'!$F$2:$F$14,A32) -> 3
A33: Transform customers | B33: =COUNTIF('13-week plan'!$F$2:$F$14,A33) -> 1
A34: Total | B34: =SUM(B30:B33) -> 13
A36: Episode status
A37: Status | B37: Count
A38: Not started | B38: =COUNTIF('13-week plan'!$O$2:$O$14,A38) -> 13
A39: In progress | B39: =COUNTIF('13-week plan'!$O$2:$O$14,A39) -> 0
A40: Ready | B40: =COUNTIF('13-week plan'!$O$2:$O$14,A40) -> 0
A41: Live | B41: =COUNTIF('13-week plan'!$O$2:$O$14,A41) -> 0
A42: Done | B42: =COUNTIF('13-week plan'!$O$2:$O$14,A42) -> 0
A43: Moved | B43: =COUNTIF('13-week plan'!$O$2:$O$14,A43) -> 0
A44: Total | B44: =SUM(B38:B43) -> 13
